{
	"data_dir": "data/article",
	"train_file": "train_dataset.json",
	"valid_file": "valid_dataset.json",
	"output_dir": "klue_roberta_large_ckpt",
	"model_type": "klue_roberta_large",
	"max_seq_length": 512,
	"no_cuda": false,
	"do_train": true,
	"do_eval": true,
	"evaluate_during_training": true,
	"model_name_or_path": "klue/roberta-large",
	"ckpt_dir": "ckpt",
	"overwrite": false,
	"seed": 52,
	"gradient_accumulation_steps": 100,
	"num_train_epochs": 10,
	"train_batch_size": 8,
	"valid_batch_size": 8,
	"logging_steps": 6000,
	"save_steps": 6000,
	"learning_rate": 0.0001,
	"adam_epsilon": 1e-08,
	"weight_decay": 0.0,
	"warmup_proportion": 0
}